{
    "close": {
        "name": "close",
        "color": "",
        "background": "",
        "icon": "close",
        "classes": ["neutral-button"]
    },
    "remove-only": {
        "name": "remove-only",
        "color": "",
        "background": "",
        "icon": "remove_circle_outline",
        "classes": ["accept-button"]
    },
    "delete": {
        "name": "delete",
        "color": "",
        "background": "",
        "icon": "delete_forever",
        "classes": ["negative-button"]
    },
    "cancel": {
        "name": "cancel",
        "color": "",
        "background": "",
        "icon": "cancel",
        "classes": ["neutral-button"]
    },
    "update": {
        "name": "update",
        "color": "",
        "background": "",
        "icon": "update",
        "classes": ["accept-button"]
    },
    "report-issue": {
        "name": "report-issue",
        "color": "",
        "background": "",
        "icon": "bug-report",
        "classes": ["accept-button"]
    },
    "quit": {
        "name": "quit",
        "color": "",
        "background": "",
        "icon": "exit_to_app",
        "classes": ["negative-button"]
    }
}